Workbook
Name Slicer_Category: #N/A
Name Slicer_Month: #N/A
Name Slicer_Segment: #N/A
Name Slicer_State: #N/A
Name Slicer_Year: #N/A
Name Timeline_Order_Date: #N/A

Sheet Orders
A1: Order_ID | B1: Order_Date | C1: Customer_ID | D1: Product_ID | E1: Quantity | F1: Sales | G1: Profit | H1: Month | I1: Year | J1: Quarter | K1: Profit Margin %
A2: O0001 | B2: 45344 | C2: C088 | D2: P008 | E2: 2 | F2: 18788 | G2: 3879.37 | H2: =TEXT(Orders[[#This Row],[Order_Date]],"mmmm") -> February | I2: =YEAR(Orders[[#This Row],[Order_Date]]) -> 2024 | J2: ="Q"&ROUNDUP(MONTH(Orders[[#This Row],[Order_Date]])/3,0) -> Q1 | K2: =(Orders[[#This Row],[Profit]]/Orders[[#This Row],[Sales]])*100 -> 20.648126
A3: O0002 | B3: 45442 | C3: C056 | D3: P013 | E3: 5 | F3: 44365 | G3: 10406.6 | H3: =TEXT(Orders[[#This Row],[Order_Date]],"mmmm") -> May | I3: =YEAR(Orders[[#This Row],[Order_Date]]) -> 2024 | J3: ="Q"&ROUNDUP(MONTH(Orders[[#This Row],[Order_Date]])/3,0) -> Q2 | K3: =(Orders[[#This Row],[Profit]]/Orders[[#This Row],[Sales]])*100 -> 23.456779
A4: O0003 | B4: 45398 | C4: C071 | D4: P009 | E4: 4 | F4: 219748 | G4: 29327.16 | H4: =TEXT(Orders[[#This Row],[Order_Date]],"mmmm") -> April | I4: =YEAR(Orders[[#This Row],[Order_Date]]) -> 2024 | J4: ="Q"&ROUNDUP(MONTH(Orders[[#This Row],[Order_Date]])/3,0) -> Q2 | K4: =(Orders[[#This Row],[Profit]]/Orders[[#This Row],[Sales]])*100 -> 13.345814
A5: O0004 | B5: 45443 | C5: C084 | D5: P011 | E5: 1 | F5: 55695 | G5: 4713.73 | H5: =TEXT(Orders[[#This Row],[Order_Date]],"mmmm") -> May | I5: =YEAR(Orders[[#This Row],[Order_Date]]) -> 2024 | J5: ="Q"&ROUNDUP(MONTH(Orders[[#This Row],[Order_Date]])/3,0) -> Q2 | K5: =(Orders[[#This Row],[Profit]]/Orders[[#This Row],[Sales]])*100 -> 8.4634707
A6: O0005 | B6: 45452 | C6: C093 | D6: P020 | E6: 3 | F6: 34026 | G6: 5324.17 | H6: =TEXT(Orders[[#This Row],[Order_Date]],"mmmm") -> June | I6: =YEAR(Orders[[#This Row],[Order_Date]]) -> 2024 | J6: ="Q"&ROUNDUP(MONTH(Orders[[#This Row],[Order_Date]])/3,0) -> Q2 | K6: =(Orders[[#This Row],[Profit]]/Orders[[#This Row],[Sales]])*100 -> 15.647358
A7: O0006 | B7: 45599 | C7: C052 | D7: P003 | E7: 1 | F7: 8626 | G7: 2029.5 | H7: =TEXT(Orders[[#This Row],[Order_Date]],"mmmm") -> November | I7: =YEAR(Orders[[#This Row],[Order_Date]]) -> 2024 | J7: ="Q"&ROUNDUP(MONTH(Orders[[#This Row],[Order_Date]])/3,0) -> Q4 | K7: =(Orders[[#This Row],[Profit]]/Orders[[#This Row],[Sales]])*100 -> 23.527707
A8: O0007 | B8: 45608 | C8: C059 | D8: P004 | E8: 3 | F8: 75477 | G8: 8799.32 | H8: =TEXT(Orders[[#This Row],[Order_Date]],"mmmm") -> November | I8: =YEAR(Orders[[#This Row],[Order_Date]]) -> 2024 | J8: ="Q"&ROUNDUP(MONTH(Orders[[#This Row],[Order_Date]])/3,0) -> Q4 | K8: =(Orders[[#This Row],[Profit]]/Orders[[#This Row],[Sales]])*100 -> 11.65828
A9: O0008 | B9: 45424 | C9: C100 | D9: P018 | E9: 4 | F9: 33448 | G9: 6439.14 | H9: =TEXT(Orders[[#This Row],[Order_Date]],"mmmm") -> May | I9: =YEAR(Orders[[#This Row],[Order_Date]]) -> 2024 | J9: ="Q"&ROUNDUP(MONTH(Orders[[#This Row],[Order_Date]])/3,0) -> Q2 | K9: =(Orders[[#This Row],[Profit]]/Orders[[#This Row],[Sales]])*100 -> 19.251196
A10: O0009 | B10: 45418 | C10: C024 | D10: P018 | E10: 2 | F10: 16724 | G10: 2211.66 | H10: =TEXT(Orders[[#This Row],[Order_Date]],"mmmm") -> May | I10: =YEAR(Orders[[#This Row],[Order_Date]]) -> 2024 | J10: ="Q"&ROUNDUP(MONTH(Orders[[#This Row],[Order_Date]])/3,0) -> Q2 | K10: =(Orders[[#This Row],[Profit]]/Orders[[#This Row],[Sales]])*100 -> 13.224468
A11: O0010 | B11: 45521 | C11: C047 | D11: P003 | E11: 3 | F11: 25878 | G11: 2463.6 | H11: =TEXT(Orders[[#This Row],[Order_Date]],"mmmm") -> August | I11: =YEAR(Orders[[#This Row],[Order_Date]]) -> 2024 | J11: ="Q"&ROUNDUP(MONTH(Orders[[#This Row],[Order_Date]])/3,0) -> Q3 | K11: =(Orders[[#This Row],[Profit]]/Orders[[#This Row],[Sales]])*100 -> 9.5200556
A12: O0011 | B12: 45491 | C12: C012 | D12: P019 | E12: 3 | F12: 72708 | G12: 17444.46 | H12: =TEXT(Orders[[#This Row],[Order_Date]],"mmmm") -> July | I12: =YEAR(Orders[[#This Row],[Order_Date]]) -> 2024 | J12: ="Q"&ROUNDUP(MONTH(Orders[[#This Row],[Order_Date]])/3,0) -> Q3 | K12: =(Orders[[#This Row],[Profit]]/Orders[[#This Row],[Sales]])*100 -> 23.992491
A13: O0012 | B13: 45588 | C13: C040 | D13: P002 | E13: 3 | F13: 33468 | G13: 3740.32 | H13: =TEXT(Orders[[#This Row],[Order_Date]],"mmmm") -> October | I13: =YEAR(Orders[[#This Row],[Order_Date]]) -> 2024 | J13: ="Q"&ROUNDUP(MONTH(Orders[[#This Row],[Order_Date]])/3,0) -> Q4 | K13: =(Orders[[#This Row],[Profit]]/Orders[[#This Row],[Sales]])*100 -> 11.17581
... A1001: O1000 | B1001: 45316 | C1001: C033 | D1001: P014 | E1001: 5 | F1001: 270935 | G1001: 43393.36 | H1001: =TEXT(Orders[[#This Row],[Order_Date]],"mmmm") -> January | I1001: =YEAR(Orders[[#This Row],[Order_Date]]) -> 2024 | J1001: ="Q"&ROUNDUP(MONTH(Orders[[#This Row],[Order_Date]])/3,0) -> Q1 | K1001: =(Orders[[#This Row],[Profit]]/Orders[[#This Row],[Sales]])*100 -> 16.016151

Sheet Customers
A1: Customer_ID | B1: Customer_Name | C1: Gender | D1: Age | E1: City | F1: State | G1: Segment
A2: C001 | B2: Customer 1 | C2: Male | D2: 25 | E2: Mumbai | F2: Maharashtra | G2: Corporate
A3: C002 | B3: Customer 2 | C3: Female | D3: 52 | E3: Pune | F3: Maharashtra | G3: Corporate
A4: C003 | B4: Customer 3 | C4: Male | D4: 45 | E4: Bengaluru | F4: Karnataka | G4: Consumer
A5: C004 | B5: Customer 4 | C5: Female | D5: 52 | E5: Pune | F5: Maharashtra | G5: Consumer
A6: C005 | B6: Customer 5 | C6: Male | D6: 48 | E6: Bengaluru | F6: Karnataka | G6: Home Office
A7: C006 | B7: Customer 6 | C7: Female | D7: 49 | E7: Pune | F7: Maharashtra | G7: Corporate
A8: C007 | B8: Customer 7 | C8: Male | D8: 27 | E8: Mumbai | F8: Maharashtra | G8: Corporate
A9: C008 | B9: Customer 8 | C9: Female | D9: 22 | E9: Pune | F9: Maharashtra | G9: Consumer
A10: C009 | B10: Customer 9 | C10: Male | D10: 21 | E10: Hyderabad | F10: Telangana | G10: Corporate
A11: C010 | B11: Customer 10 | C11: Female | D11: 48 | E11: Mumbai | F11: Maharashtra | G11: Home Office
A12: C011 | B12: Customer 11 | C12: Male | D12: 54 | E12: Pune | F12: Maharashtra | G12: Consumer
A13: C012 | B13: Customer 12 | C13: Female | D13: 52 | E13: Bengaluru | F13: Karnataka | G13: Home Office
... A101: C100 | B101: Customer 100 | C101: Female | D101: 28 | E101: Delhi | F101: Delhi | G101: Home Office

Sheet Products
A1: Product_ID | B1: Product_Name | C1: Category | D1: Sub_Category | E1: Unit_Price
A2: P001 | B2: Table 1 | C2: Furniture | D2: Tables | E2: 9101
A3: P002 | B3: Printer 2 | C3: Technology | D3: Accessories | E3: 11156
A4: P003 | B4: Table 3 | C4: Furniture | D4: Tables | E4: 8626
A5: P004 | B5: Mobile 4 | C5: Technology | D5: Phones | E5: 25159
A6: P005 | B6: Laptop 5 | C6: Technology | D6: Computers | E6: 55950
A7: P006 | B7: Chair 6 | C7: Furniture | D7: Chairs | E7: 6747
A8: P007 | B8: Chair 7 | C8: Furniture | D8: Chairs | E8: 7155
A9: P008 | B9: Table 8 | C9: Furniture | D9: Tables | E9: 9394
A10: P009 | B10: Laptop 9 | C10: Technology | D10: Computers | E10: 54937
A11: P010 | B11: Chair 10 | C11: Furniture | D11: Chairs | E11: 6220
A12: P011 | B12: Laptop 11 | C12: Technology | D12: Computers | E12: 55695
A13: P012 | B13: Chair 12 | C13: Furniture | D13: Chairs | E13: 6025
... A21: P020 | B21: Printer 20 | C21: Technology | D21: Accessories | E21: 11342

Sheet Returns
A1: Order_ID | B1: Returned
A2: O0001 | B2: No
A3: O0002 | B3: No
A4: O0003 | B4: No
A5: O0004 | B5: Yes
A6: O0005 | B6: Yes
A7: O0006 | B7: No
A8: O0007 | B8: No
A9: O0008 | B9: No
A10: O0009 | B10: No
A11: O0010 | B11: No
A12: O0011 | B12: No
... A1001: O1000 | B1001: No

Sheet Sheet6
A3: Row Labels | B3: Sum of Sales
A4: Delhi | B4: 814238
A5: Karnataka | B5: 673620
A6: Maharashtra | B6: 2412106
A7: Telangana | B7: 2328675
A8: Grand Total | B8: 6228639

Sheet Sheet5
A3: Row Labels | B3: Sum of Sales
A4: Laptop 11 | B4: 779730
A5: Laptop 14 | B5: 379309
A6: Laptop 16 | B6: 761376
A7: Laptop 5 | B7: 839250
A8: Laptop 9 | B8: 1153677
A9: Mobile 17 | B9: 307296
A10: Printer 2 | B10: 189652
A11: Printer 20 | B11: 408312
A12: Table 13 | B12: 204079
A13: Table 8 | B13: 206668
A14: Grand Total | B14: 5229349

Sheet Sheet7
A3: Row Labels | B3: Sum of Sales
A4: Consumer | B4: 1323211
A5: Corporate | B5: 2455772
A6: Home Office | B6: 2449656
A7: Grand Total | B7: 6228639

Sheet Sheet8
A3: Row Labels | B3: Sum of Sales
A4: Furniture | B4: 1111422
A5: Technology | B5: 5117217
A6: Grand Total | B6: 6228639

Sheet Sheet10
A3: Row Labels | B3: Count of Order_ID
A4: No | B4: 96
A5: Yes | B5: 96
A6: Grand Total | B6: 96

Sheet Pivot
B4: Row Labels | C4: Sum of Sales | E4: =SUM(Orders!F:F) -> 68871275 | G4: Row Labels | H4: Sum of Profit
B5: January | C5: 5612793 | G5: January | H5: 896163.16
B6: February | C6: 5806774 | G6: February | H6: 1007139
B7: March | C7: 7018340 | E7: =SUM(Orders!G:G) -> 11366566 | G7: March | H7: 1122442.5
B8: April | C8: 4211063 | G8: April | H8: 707760.06
B9: May | C9: 6228639 | E9: =COUNTA(Orders!A:A)-1 -> 1000 | G9: May | H9: 1061846.9
B10: June | C10: 4224834 | G10: June | H10: 696198.28
B11: July | C11: 6274616 | G11: July | H11: 997191.67
B12: August | C12: 4929801 | E12: =AVERAGE(Orders!F:F) -> 68871.275 | G12: August | H12: 846930.81
B13: September | C13: 5778966 | G13: September | H13: 959478.32
B14: October | C14: 6761972 | E14: =SUM(Orders!E:E) -> 3011 | G14: October | H14: 1080079.9
B15: November | C15: 6067924 | E15: =SUM(Orders[Quantity]) -> 3011 | G15: November | H15: 1028974.3
B16: December | C16: 5955553 | G16: December | H16: 962360.75
B17: Grand Total | C17: 68871275 | G17: Grand Total | H17: 11366566

Sheet Dashboard
A1: E-Commerce Sales Dashboard
A52: ------------------------------------------------------------ | G52: ------------------------------------------------------------
A53: Business Insights
A54: ------------------------------------------------------------ | G54: ------------------------------------------------------------
A55: • Highest Sales Month: November
A56: • Top Performing Category: Technology
A57: • Best Selling Product: Laptop
A58: • Top Customer: Customer 25
A59: • Highest Sales State: Maharashtra
A60: • Total Return Rate: 8%
A61: • Recommendation: Increase inventory for top-selling products.
